cdproj
