Metadata-Version: 1.1
Name: cdproj
Version: 0.0.6
Summary: A really simple langage-independent project manager.
Home-page: https://github.com/paulollivier/cdproj
Author: Paul Ollivier
Author-email: contact@paulollivier.fr
License: MIT
Platform: UNKNOWN
Classifier: Development Status :: 3 - Alpha
Classifier: Intended Audience :: Developers
Classifier: Programming Language :: Python
Classifier: Programming Language :: Python :: 2.7
